vml_parser/__init__.py
vml_parser/vml.py
vml_parser-0.0.15.dist-info/LICENSE
vml_parser-0.0.15.dist-info/METADATA
vml_parser-0.0.15.dist-info/WHEEL
vml_parser-0.0.15.dist-info/entry_points.txt
vml_parser-0.0.15.dist-info/top_level.txt
vml_parser-0.0.15.dist-info/RECORD
