Metadata-Version: 2.1
Name: vml-parser
Version: 0.0.15
Summary: velocitous markup language to JSON parser
Author-email: Valerio Iacobucci <valerio@valerioiacobucci.com>
Project-URL: Homepage, https://github.com/iacobucci/vml
Classifier: Programming Language :: Python :: 3
Classifier: License :: OSI Approved :: MIT License
Classifier: Operating System :: OS Independent
Requires-Python: >=3.7
License-File: LICENSE
